EzDocxTemplate/EzDocxTemplate.py
EzDocxTemplate/__init__.py
EzDocxTemplate-0.1.0.dist-info/LICENSE
EzDocxTemplate-0.1.0.dist-info/METADATA
EzDocxTemplate-0.1.0.dist-info/WHEEL
EzDocxTemplate-0.1.0.dist-info/top_level.txt
EzDocxTemplate-0.1.0.dist-info/RECORD
