Metadata-Version: 2.2
Name: EzDocxTemplate
Version: 0.1.0
Summary: A Python module for easily modifying docx templates
Author-email: Rarder44 <luca@lpozzi.it>
License: GPL-3
Project-URL: Repository, https://github.com/Rarder44/EzDocxTemplate
Classifier: Programming Language :: Python :: 3
Classifier: License :: OSI Approved :: GNU General Public License v3 (GPLv3)
Classifier: Operating System :: OS Independent
License-File: LICENSE
Requires-Dist: python-docx
